factory_component/Example.py
factory_component/Rnd.py
factory_component/TextEditor.py
factory_component/__init__.py
factory_component/_imports_.py
factory_component/factory_component.min.js
factory_component/factory_component.min.js.map
factory_component/metadata.json
factory_component/package-info.json
factory_component-0.0.8.dist-info/LICENSE
factory_component-0.0.8.dist-info/METADATA
factory_component-0.0.8.dist-info/WHEEL
factory_component-0.0.8.dist-info/top_level.txt
factory_component-0.0.8.dist-info/RECORD
