Metadata-Version: 2.1
Name: factory-component
Version: 0.0.8
Summary: Project Description
Author: lucas <lucasprett129@gmail.com>
License: MIT
Platform: UNKNOWN
Classifier: Framework :: Dash
License-File: LICENSE
